pyonvif/__init__.py
pyonvif/cmdline.py
pyonvif/messages.py
pyonvif/namespaces.py
pyonvif/pyonvif.py
pyOnvif-1.1.dist-info/LICENSE.txt
pyOnvif-1.1.dist-info/METADATA
pyOnvif-1.1.dist-info/WHEEL
pyOnvif-1.1.dist-info/entry_points.txt
pyOnvif-1.1.dist-info/top_level.txt
pyOnvif-1.1.dist-info/RECORD
