Metadata-Version: 2.1
Name: pyOnvif
Version: 1.1
Summary: Simple Onvif camera client
Home-page: https://github.com/koodaamo/pyOnvif
Author: Pekka Jäppinen
Maintainer: Petri Savolainen
License: GPLv3
Keywords: onvif
Platform: UNKNOWN
Classifier: Development Status :: 4 - Beta
Classifier: Intended Audience :: Developers
Classifier: License :: OSI Approved :: GNU General Public License v3 (GPLv3)
Classifier: Programming Language :: Python :: 3
Classifier: Programming Language :: Python :: 3.5
Classifier: Programming Language :: Python :: 3.6
Classifier: Programming Language :: Python :: 3.7
Provides-Extra: discovery
Requires-Dist: WSDiscovery ; extra == 'discovery'
